streamlit_geolocation/__init__.py
streamlit_geolocation/example.py
streamlit_geolocation/frontend/build/asset-manifest.json
streamlit_geolocation/frontend/build/bootstrap.min.css
streamlit_geolocation/frontend/build/index.html
streamlit_geolocation/frontend/build/static/js/main.72eca811.js
streamlit_geolocation/frontend/build/static/js/main.72eca811.js.LICENSE.txt
streamlit_geolocation/frontend/build/static/js/main.72eca811.js.map
streamlit_geolocation-0.0.10.dist-info/LICENSE
streamlit_geolocation-0.0.10.dist-info/METADATA
streamlit_geolocation-0.0.10.dist-info/WHEEL
streamlit_geolocation-0.0.10.dist-info/top_level.txt
streamlit_geolocation-0.0.10.dist-info/RECORD
