Metadata-Version: 2.1
Name: streamlit-geolocation
Version: 0.0.10
Summary: A custom Streamlit component to get the users location via js navigator.geolocation.
Home-page: https://github.com/steffanic/streamlit-geolocation
Author: Patrick Steffanic
Author-email: steffaniccodes@gmail.com
Keywords: Python,Streamlit,JavaScript
Requires-Python: >=3.8
License-File: LICENSE
Requires-Dist: streamlit>=1.0.0
